{
  "timestamp": "2025-10-21T10:11:27.692595",
  "well_name": "Bagn_01:Asm",
  "district": "Bahregan",
  "field": "Bahregan_Sar",
  "formation": "Asm",
  "start_method": "manual",
  "manual_year": "1963",
  "manual_month": "9",
  "qi_year": "2020",
  "qi_month": "1",
  "qi_value": "",
  "fixed_qi": null,
  "threshold": "2.2",
  "threshold_opt": false,
  "forecast_avg_points": "The Last Rate",
  "forecast_duration": "60",
  "forecast_offset": "0",
  "smooth_window": "13",
  "smooth_window_opt": true,
  "min_segment_length": "15",
  "min_segment_length_opt": true,
  "change_sensitivity": "0.1",
  "change_sensitivity_opt": false,
  "stability_window": "10",
  "stability_window_opt": false,
  "min_decline_rate": "0.05",
  "min_decline_rate_opt": true,
  "show_outliers": true,
  "show_pre_decline": true,
  "show_forecast": true,
  "show_smoothed": false,
  "show_channel": false,
  "optimize": true,
  "results_text": "\n=== Final Results for well Bagn_01:Asm ===\nTotal outliers removed: 4 out of 96 points\nFitted parameters:\nqi = 6630.22, Di = 0.0141, b = 0.00\n\nCoefficient of Variation: 0.518\n\u26a0 WARNING: High variability detected. Forecast may be unreliable.\n",
  "analysis_params": {
    "outlier_threshold": 2.2,
    "forecast_avg_points": 1,
    "manual_start_idx": 